pezin/__init__.py
pezin/logging.py
pezin/cli/__init__.py
pezin/cli/commands.py
pezin/cli/hooks.py
pezin/cli/main.py
pezin/cli/utils.py
pezin/core/__init__.py
pezin/core/changelog.py
pezin/core/commit.py
pezin/core/handlers.py
pezin/core/version.py
pezin/hooks/__init__.py
pezin/hooks/post_commit.py
pezin/hooks/pre_commit.py
pezin/hooks/prepare_commit_msg.py
pezin-0.2.1.dist-info/METADATA
pezin-0.2.1.dist-info/WHEEL
pezin-0.2.1.dist-info/entry_points.txt
pezin-0.2.1.dist-info/top_level.txt
pezin-0.2.1.dist-info/RECORD
