Metadata-Version: 2.4
Name: pezin
Version: 0.2.1
Summary: Automated version bumping and changelog management using conventional commits
Author-email: Tatus9 <rafael@rro.one>
Requires-Python: >=3.12
Requires-Dist: packaging>=25.0
Requires-Dist: rich>=14.0.0
Requires-Dist: typer>=0.16.0
Requires-Dist: tomli>=2.0.0
Requires-Dist: tomli-w>=1.0.0
Requires-Dist: loguru>=0.7.3
Requires-Dist: pre-commit>=3.0.0
